{
  "__fct":
    {
      "loops":
        {
          "_8036":
            {
              "src_regions":
                [
                ],
              "src": "",
            },
          "_8035":
            {
              "src_regions":
                [
                ],
              "src": "",
            },
          "_8037":
            {
              "_8038":
                {
                  "src_regions":
                    [
                    ],
                  "src": "",
                },
              "src_regions":
                [
                ],
              "src": "",
            },
        },
    },
}
