{
  "__fct":
    {
      "loops":
        {
          "_2453":
            {
              "src_regions":
                [
                  {
                    "path": "/usr/local/src/conda/python-3.9.19/Objects/longobject.c",
                    "regions":
                      [
                        [
                        695,
                        698,
                        ],
                      ],
                  },
                ],
              "src": "longobject.c:695-698",
            },
          "_2452":
            {
              "src_regions":
                [
                  {
                    "path": "/usr/local/src/conda/python-3.9.19/Objects/longobject.c",
                    "regions":
                      [
                        [
                        676,
                        676,
                        ],
                        [
                        699,
                        706,
                        ],
                      ],
                  },
                ],
              "src": "longobject.c:676-706",
            },
        },
    },
}
