{
  "_cqa_text_report":
    {
      "_objects":
        {
          "image_vec_align":
            {
              "type": "image",
              "format": "url",
              "data": "../images/cqa/vec_align.svg",
              "size":
                {
                  "x": 500,
                },
            },
          "image_1x64_512":
            {
              "type": "image",
              "format": "url",
              "data": "../images/cqa/1x64_512.svg",
              "size":
                {
                  "x": 500,
                },
            },
          "image_1x32_128":
            {
              "type": "image",
              "format": "url",
              "data": "../images/cqa/1x32_128.svg",
              "size":
                {
                  "x": 500,
                },
            },
          "image_4x32_256":
            {
              "type": "image",
              "format": "url",
              "data": "../images/cqa/4x32_256.svg",
              "size":
                {
                  "x": 500,
                },
            },
          "image_1x64_128":
            {
              "type": "image",
              "format": "url",
              "data": "../images/cqa/1x64_128.svg",
              "size":
                {
                  "x": 500,
                },
            },
          "image_4x32_512":
            {
              "type": "image",
              "format": "url",
              "data": "../images/cqa/4x32_512.svg",
              "size":
                {
                  "x": 500,
                },
            },
          "image_8x32_512":
            {
              "type": "image",
              "format": "url",
              "data": "../images/cqa/8x32_512.svg",
              "size":
                {
                  "x": 500,
                },
            },
          "image_1x32_256":
            {
              "type": "image",
              "format": "url",
              "data": "../images/cqa/1x32_256.svg",
              "size":
                {
                  "x": 500,
                },
            },
          "image_2x64_512":
            {
              "type": "image",
              "format": "url",
              "data": "../images/cqa/2x64_512.svg",
              "size":
                {
                  "x": 500,
                },
            },
          "image_2x64_256":
            {
              "type": "image",
              "format": "url",
              "data": "../images/cqa/2x64_256.svg",
              "size":
                {
                  "x": 500,
                },
            },
          "image_1x64_256":
            {
              "type": "image",
              "format": "url",
              "data": "../images/cqa/1x64_256.svg",
              "size":
                {
                  "x": 500,
                },
            },
          "image_1x32_512":
            {
              "type": "image",
              "format": "url",
              "data": "../images/cqa/1x32_512.svg",
              "size":
                {
                  "x": 500,
                },
            },
          "image_4x64_512":
            {
              "type": "image",
              "format": "url",
              "data": "../images/cqa/4x64_512.svg",
              "size":
                {
                  "x": 500,
                },
            },
          "image_row_maj":
            {
              "type": "image",
              "format": "url",
              "data": "../images/cqa/row_maj.svg",
              "size":
                {
                  "x": 500,
                },
            },
          "image_col_maj":
            {
              "type": "image",
              "format": "url",
              "data": "../images/cqa/col_maj.svg",
              "size":
                {
                  "x": 500,
                },
            },
        },
      "AVG":
        {
          "hint":
            [
              {
                "details": "Calling (and then returning from) a function prevents many compiler optimizations (like vectorization), breaks control flow (which reduces pipeline performance) and executes extra instructions to save/restore the registers used inside it, which is very expensive (dozens of cycles). Consider to inline small functions.\n - _PyUnicodeWriter_PrepareInternal@plt: 1 occurrences\n - _PyUnicodeWriter_WriteSubstring@plt: 1 occurrences\n",
                "title": "CALL instructions",
                "txt": "Detected function call instructions.\n",
              },
              {
                "details": "These instructions generate more than one micro-operation and only one of them can be decoded during a cycle and the extra micro-operations increase pressure on execution units.\n - VZEROUPPER: 2 occurrences\n",
                "title": "Complex instructions",
                "txt": "Detected COMPLEX INSTRUCTIONS.\n",
              },
              {
                "title": "Type of elements and instruction set",
                "txt": "No instructions are processing arithmetic or math operations on FP elements. This loop is probably writing/copying data or processing integer elements.",
              },
              {
                "title": "Matching between your loop (in the source code) and the binary loop",
                "txt": "The binary loop does not contain any FP arithmetical operations.\nThe binary loop is loading 150 bytes.\nThe binary loop is storing 152 bytes.",
              },
            ],
          "expert":
            [
              {
                "title": "General properties",
                "txt": "nb instructions    : 112\nnb uops            : 120\nloop length        : 540\nused x86 registers : 12\nused mmx registers : 0\nused xmm registers : 0\nused ymm registers : 0\nused zmm registers : 0\nnb stack references: 14\n",
              },
              {
                "title": "Front-end",
                "txt": "MACRO FUSION NOT POSSIBLE\nFIT IN UOP CACHE\nmicro-operation queue: 24.00 cycles\nfront end            : 24.00 cycles\n",
              },
              {
                "title": "Back-end",
                "txt": "       | P0    | P1    | P2    | P3    | P4    | P5    | P6    | P7    | P8    | P9\n--------------------------------------------------------------------------------------\nuops   | 15.75 | 15.75 | 12.50 | 12.50 | 12.00 | 15.75 | 15.75 | 12.00 | 12.00 | 12.00\ncycles | 15.75 | 15.75 | 12.50 | 12.50 | 12.00 | 15.75 | 15.75 | 12.00 | 12.00 | 12.00\n\nExecution ports to units layout:\n - P0 (256 bits): VPU, ALU, DIV/SQRT\n - P1 (256 bits): ALU, VPU\n - P2 (512 bits): load\n - P3 (512 bits): load\n - P4 (256 bits): store data\n - P5 (512 bits): ALU, VPU\n - P6: ALU\n - P7: store address\n - P8: store address\n - P9 (256 bits): store data\n\nCycles executing div or sqrt instructions: NA\n",
              },
              {
                "title": "Cycles summary",
                "txt": "Front-end : 24.00\nDispatch  : 15.75\nOverall L1: 24.00\n",
              },
              {
                "title": "Vectorization ratios",
                "txt": "all     : 4%\nload    : 0%\nstore   : 0%\nmul     : NA (no mul vectorizable/vectorized instructions)\nadd-sub : NA (no add-sub vectorizable/vectorized instructions)\nfma     : NA (no fma vectorizable/vectorized instructions)\ndiv/sqrt: NA (no div/sqrt vectorizable/vectorized instructions)\nother   : 11%\n",
              },
              {
                "title": "Vector efficiency ratios",
                "txt": "all     : 9%\nload    : 6%\nstore   : 10%\nmul     : NA (no mul vectorizable/vectorized instructions)\nadd-sub : NA (no add-sub vectorizable/vectorized instructions)\nfma     : NA (no fma vectorizable/vectorized instructions)\ndiv/sqrt: NA (no div/sqrt vectorizable/vectorized instructions)\nother   : 8%\n",
              },
              {
                "title": "Cycles and memory resources usage",
                "txt": "Assuming all data fit into the L1 cache, each iteration of the binary loop takes 24.00 cycles. At this rate:\n - 4% of peak load performance is reached (6.25 out of 128.00 bytes loaded per cycle (GB/s @ 1GHz))\n - 9% of peak store performance is reached (6.33 out of 64.00 bytes stored per cycle (GB/s @ 1GHz))\n",
              },
              {
                "title": "Front-end bottlenecks",
                "txt": "Performance is limited by instruction throughput (loading/decoding program instructions to execution core) (front-end is a bottleneck).\n\nBy removing all these bottlenecks, you can lower the cost of an iteration from 24.00 to 15.75 cycles (1.52x speedup).\n",
              },
              {
                "title": "ASM code",
                "txt": "In the binary file, the address of the loop is: 246a9b\n\nInstruction                                        | Nb FU | P0   | P1   | P2   | P3   | P4   | P5   | P6   | P7   | P8   | P9   | Latency | Recip. throughput\n--------------------------------------------------------------------------------------------------------------------------------------------------------------\nMOV -0x88(%RBP),%R8                                | 1     | 0    | 0    | 0.50 | 0.50 | 0    | 0    | 0    | 0    | 0    | 0    | 2       | 0.50\nMOV -0x98(%RBP),%EDX                               | 1     | 0    | 0    | 0.50 | 0.50 | 0    | 0    | 0    | 0    | 0    | 0    | 2       | 0.50\nMOV -0x80(%RBP),%RSI                               | 1     | 0    | 0    | 0.50 | 0.50 | 0    | 0    | 0    | 0    | 0    | 0    | 2       | 0.50\nMOV %EDX,%R9D                                      | 1     | 0.25 | 0.25 | 0    | 0    | 0    | 0.25 | 0.25 | 0    | 0    | 0    | 1       | 0.25\nLEA 0x1(%R8),%RCX                                  | 1     | 0.25 | 0.25 | 0    | 0    | 0    | 0.25 | 0.25 | 0    | 0    | 0    | 1       | 0.25\nCMP $0x1,%EDX                                      | 1     | 0.25 | 0.25 | 0    | 0    | 0    | 0.25 | 0.25 | 0    | 0    | 0    | 1       | 0.25\nJE 2473a0 <PyUnicode_Format+0xaf0>                 | 1     | 0.50 | 0    | 0    | 0    | 0    | 0    | 0.50 | 0    | 0    | 0    | 0       | 0.50-1\nCMP $0x2,%EDX                                      | 1     | 0.25 | 0.25 | 0    | 0    | 0    | 0.25 | 0.25 | 0    | 0    | 0    | 1       | 0.25\nJE 2473e8 <PyUnicode_Format+0xb38>                 | 1     | 0.50 | 0    | 0    | 0    | 0    | 0    | 0.50 | 0    | 0    | 0    | 0       | 0.50-1\nCMPL $0x25,(%RSI,%R8,4)                            | 1     | 0.25 | 0.25 | 0.50 | 0.50 | 0    | 0.25 | 0.25 | 0    | 0    | 0    | 1       | 0.50\nLEA (,%R8,4),%R10                                  | 1     | 0.25 | 0.25 | 0    | 0    | 0    | 0.25 | 0.25 | 0    | 0    | 0    | 1       | 0.25\nMOV %RCX,-0x88(%RBP)                               | 1     | 0    | 0    | 0    | 0    | 0.50 | 0    | 0    | 0.50 | 0.50 | 0.50 | 3       | 0.50\nJE 246b10 <PyUnicode_Format+0x260>                 | 1     | 0.50 | 0    | 0    | 0    | 0    | 0    | 0.50 | 0    | 0    | 0    | 0       | 0.50-1\nXOR %EDI,%EDI                                      | 1     | 0    | 0    | 0    | 0    | 0    | 0    | 0    | 0    | 0    | 0    | 0       | 0.25\nXOR %EDX,%EDX                                      | 1     | 0    | 0    | 0    | 0    | 0    | 0    | 0    | 0    | 0    | 0    | 0       | 0.25\nJMP 246a60 <PyUnicode_Format+0x1b0>                | 1     | 0    | 0    | 0    | 0    | 0    | 0    | 1    | 0    | 0    | 0    | 0       | 1-2\nTEST %DIL,%DIL                                     | 1     | 0.25 | 0.25 | 0    | 0    | 0    | 0.25 | 0.25 | 0    | 0    | 0    | 1       | 0.25\nJE 246a72 <PyUnicode_Format+0x1c2>                 | 1     | 0.50 | 0    | 0    | 0    | 0    | 0    | 0.50 | 0    | 0    | 0    | 0       | 0.50-1\nMOV %R13,-0x90(%RBP)                               | 1     | 0    | 0    | 0    | 0    | 0.50 | 0    | 0    | 0.50 | 0.50 | 0.50 | 3       | 0.50\nTEST %DL,%DL                                       | 1     | 0.25 | 0.25 | 0    | 0    | 0    | 0.25 | 0.25 | 0    | 0    | 0    | 1       | 0.25\nJE 246a7d <PyUnicode_Format+0x1cd>                 | 1     | 0.50 | 0    | 0    | 0    | 0    | 0    | 0.50 | 0    | 0    | 0    | 0       | 0.50-1\nMOV %R14,-0x88(%RBP)                               | 1     | 0    | 0    | 0    | 0    | 0.50 | 0    | 0    | 0.50 | 0.50 | 0.50 | 3       | 0.50\nMOV -0x78(%RBP),%RSI                               | 1     | 0    | 0    | 0.50 | 0.50 | 0    | 0    | 0    | 0    | 0    | 0    | 2       | 0.50\nMOV -0xd8(%RBP),%RDI                               | 1     | 0    | 0    | 0.50 | 0.50 | 0    | 0    | 0    | 0    | 0    | 0    | 2       | 0.50\nMOV %R8,%RDX                                       | 1     | 0.25 | 0.25 | 0    | 0    | 0    | 0.25 | 0.25 | 0    | 0    | 0    | 1       | 0.25\nVZEROUPPER                                         | 4     | 0    | 0    | 0    | 0    | 0    | 0    | 0    | 0    | 0    | 0    | 0       | 1\nCALL 1074f0 <_PyUnicodeWriter_WriteSubstring@plt>  | 2     | 0    | 0    | 0    | 0    | 0.50 | 0    | 1    | 0.50 | 0.50 | 0.50 | 0       | 2\nTEST %EAX,%EAX                                     | 1     | 0.25 | 0.25 | 0    | 0    | 0    | 0.25 | 0.25 | 0    | 0    | 0    | 1       | 0.25\nJS 246ff1 <PyUnicode_Format+0x741>                 | 1     | 0.50 | 0    | 0    | 0    | 0    | 0    | 0.50 | 0    | 0    | 0    | 0       | 0.50-1\nMOV -0x90(%RBP),%RDI                               | 1     | 0    | 0    | 0.50 | 0.50 | 0    | 0    | 0    | 0    | 0    | 0    | 2       | 0.50\nLEA -0x1(%RDI),%RAX                                | 1     | 0.25 | 0.25 | 0    | 0    | 0    | 0.25 | 0.25 | 0    | 0    | 0    | 1       | 0.25\nMOV %RAX,-0x90(%RBP)                               | 1     | 0    | 0    | 0    | 0    | 0.50 | 0    | 0    | 0.50 | 0.50 | 0.50 | 3       | 0.50\nTEST %RAX,%RAX                                     | 1     | 0.25 | 0.25 | 0    | 0    | 0    | 0.25 | 0.25 | 0    | 0    | 0    | 1       | 0.25\nJNS 2469e8 <PyUnicode_Format+0x138>                | 1     | 0.50 | 0    | 0    | 0    | 0    | 0    | 0.50 | 0    | 0    | 0    | 0       | 0.50-1\nMOV 0x4(%RSI,%R10,1),%R15D                         | 1     | 0    | 0    | 0.50 | 0.50 | 0    | 0    | 0    | 0    | 0    | 0    | 2       | 0.50\nCMP $0x25,%R15D                                    | 1     | 0.25 | 0.25 | 0    | 0    | 0    | 0.25 | 0.25 | 0    | 0    | 0    | 1       | 0.25\nJE 2474a0 <PyUnicode_Format+0xbf0>                 | 1     | 0.50 | 0    | 0    | 0    | 0    | 0    | 0.50 | 0    | 0    | 0    | 0       | 0.50-1\nMOV %R9,-0x108(%RBP)                               | 1     | 0    | 0    | 0    | 0    | 0.50 | 0    | 0    | 0.50 | 0.50 | 0.50 | 3       | 0.50\nMOV %R10,-0x100(%RBP)                              | 1     | 0    | 0    | 0    | 0    | 0.50 | 0    | 0    | 0.50 | 0.50 | 0.50 | 3       | 0.50\nMOVQ $-0x1,-0x90(%RBP)                             | 1     | 0    | 0    | 0    | 0    | 0.50 | 0    | 0    | 0.50 | 0.50 | 0.50 | 2       | 0.50\nDEC %RCX                                           | 1     | 0.25 | 0.25 | 0    | 0    | 0    | 0.25 | 0.25 | 0    | 0    | 0    | 1       | 0.25\nMOVB $0,-0x3c(%RBP)                                | 1     | 0    | 0    | 0    | 0    | 0.50 | 0    | 0    | 0.50 | 0.50 | 0.50 | 2       | 0.50\nMOV %RCX,-0x88(%RBP)                               | 1     | 0    | 0    | 0    | 0    | 0.50 | 0    | 0    | 0.50 | 0.50 | 0.50 | 3       | 0.50\nJMP 246a7d <PyUnicode_Format+0x1cd>                | 1     | 0    | 0    | 0    | 0    | 0    | 0    | 1    | 0    | 0    | 0    | 0       | 1-2\nCMPB $0x25,(%RSI,%R8,1)                            | 1     | 0.25 | 0.25 | 0.50 | 0.50 | 0    | 0.25 | 0.25 | 0    | 0    | 0    | 1       | 0.50\nMOV %RCX,-0x88(%RBP)                               | 1     | 0    | 0    | 0    | 0    | 0.50 | 0    | 0    | 0.50 | 0.50 | 0.50 | 3       | 0.50\nJNE 2473da <PyUnicode_Format+0xb2a>                | 1     | 0.50 | 0    | 0    | 0    | 0    | 0    | 0.50 | 0    | 0    | 0    | 0       | 0.50-1\nJMP 2476b0 <PyUnicode_Format+0xe00>                | 1     | 0    | 0    | 0    | 0    | 0    | 0    | 1    | 0    | 0    | 0    | 0       | 1-2\nJMP 246a7d <PyUnicode_Format+0x1cd>                | 1     | 0    | 0    | 0    | 0    | 0    | 0    | 1    | 0    | 0    | 0    | 0       | 1-2\nCMPW $0x25,(%RSI,%R8,2)                            | 1     | 0.25 | 0.25 | 0.50 | 0.50 | 0    | 0.25 | 0.25 | 0    | 0    | 0    | 1       | 0.50\nLEA (%R8,%R8,1),%R10                               | 1     | 0.25 | 0.25 | 0    | 0    | 0    | 0.25 | 0.25 | 0    | 0    | 0    | 1       | 0.25\nJE 247718 <PyUnicode_Format+0xe68>                 | 1     | 0.50 | 0    | 0    | 0    | 0    | 0    | 0.50 | 0    | 0    | 0    | 0       | 0.50-1\nMOV %RCX,-0x88(%RBP)                               | 1     | 0    | 0    | 0    | 0    | 0.50 | 0    | 0    | 0.50 | 0.50 | 0.50 | 3       | 0.50\nMOV -0x108(%RBP),%R9                               | 1     | 0    | 0    | 0.50 | 0.50 | 0    | 0    | 0    | 0    | 0    | 0    | 2       | 0.50\nXOR %EDI,%EDI                                      | 1     | 0    | 0    | 0    | 0    | 0    | 0    | 0    | 0    | 0    | 0    | 0       | 0.25\nXOR %EDX,%EDX                                      | 1     | 0    | 0    | 0    | 0    | 0    | 0    | 0    | 0    | 0    | 0    | 0       | 0.25\nMOV -0x100(%RBP),%R10                              | 1     | 0    | 0    | 0.50 | 0.50 | 0    | 0    | 0    | 0    | 0    | 0    | 2       | 0.50\nJMP 247460 <PyUnicode_Format+0xbb0>                | 1     | 0    | 0    | 0    | 0    | 0    | 0    | 1    | 0    | 0    | 0    | 0       | 1-2\nMOV %R9,-0x108(%RBP)                               | 1     | 0    | 0    | 0    | 0    | 0.50 | 0    | 0    | 0.50 | 0.50 | 0.50 | 3       | 0.50\nMOV %R10,-0x100(%RBP)                              | 1     | 0    | 0    | 0    | 0    | 0.50 | 0    | 0    | 0.50 | 0.50 | 0.50 | 3       | 0.50\nTEST %DIL,%DIL                                     | 1     | 0.25 | 0.25 | 0    | 0    | 0    | 0.25 | 0.25 | 0    | 0    | 0    | 1       | 0.25\nJE 247481 <PyUnicode_Format+0xbd1>                 | 1     | 0.50 | 0    | 0    | 0    | 0    | 0    | 0.50 | 0    | 0    | 0    | 0       | 0.50-1\nMOV %R9,-0x90(%RBP)                                | 1     | 0    | 0    | 0    | 0    | 0.50 | 0    | 0    | 0.50 | 0.50 | 0.50 | 3       | 0.50\nTEST %DL,%DL                                       | 1     | 0.25 | 0.25 | 0    | 0    | 0    | 0.25 | 0.25 | 0    | 0    | 0    | 1       | 0.25\nJE 246a7d <PyUnicode_Format+0x1cd>                 | 1     | 0.50 | 0    | 0    | 0    | 0    | 0    | 0.50 | 0    | 0    | 0    | 0       | 0.50-1\nMOV -0x100(%RBP),%RAX                              | 1     | 0    | 0    | 0.50 | 0.50 | 0    | 0    | 0    | 0    | 0    | 0    | 2       | 0.50\nMOV %RAX,-0x88(%RBP)                               | 1     | 0    | 0    | 0    | 0    | 0.50 | 0    | 0    | 0.50 | 0.50 | 0.50 | 3       | 0.50\nJMP 246a7d <PyUnicode_Format+0x1cd>                | 1     | 0    | 0    | 0    | 0    | 0    | 0    | 1    | 0    | 0    | 0    | 0       | 1-2\nADD $0x2,%R8                                       | 1     | 0.25 | 0.25 | 0    | 0    | 0    | 0.25 | 0.25 | 0    | 0    | 0    | 1       | 0.25\nSUB $0x2,%RDI                                      | 1     | 0.25 | 0.25 | 0    | 0    | 0    | 0.25 | 0.25 | 0    | 0    | 0    | 1       | 0.25\nCMPL $0x24,-0x5c(%RBP)                             | 1     | 0.25 | 0.25 | 0.50 | 0.50 | 0    | 0.25 | 0.25 | 0    | 0    | 0    | 1       | 0.50\nMOV %R8,-0x88(%RBP)                                | 1     | 0    | 0    | 0    | 0    | 0.50 | 0    | 0    | 0.50 | 0.50 | 0.50 | 3       | 0.50\nMOV %RDI,-0x90(%RBP)                               | 1     | 0    | 0    | 0    | 0    | 0.50 | 0    | 0    | 0.50 | 0.50 | 0.50 | 3       | 0.50\nJBE 2476c0 <PyUnicode_Format+0xe10>                | 1     | 0.50 | 0    | 0    | 0    | 0    | 0    | 0.50 | 0    | 0    | 0    | 0       | 0.50-1\nMOV -0x50(%RBP),%RAX                               | 1     | 0    | 0    | 0.50 | 0.50 | 0    | 0    | 0    | 0    | 0    | 0    | 2       | 0.50\nMOV -0x58(%RBP),%RDX                               | 1     | 0    | 0    | 0.50 | 0.50 | 0    | 0    | 0    | 0    | 0    | 0    | 2       | 0.50\nSUB %RAX,%RDX                                      | 1     | 0.25 | 0.25 | 0    | 0    | 0    | 0.25 | 0.25 | 0    | 0    | 0    | 1       | 0.25\nTEST %RDX,%RDX                                     | 1     | 0.25 | 0.25 | 0    | 0    | 0    | 0.25 | 0.25 | 0    | 0    | 0    | 1       | 0.25\nJLE 2476c0 <PyUnicode_Format+0xe10>                | 1     | 0.50 | 0    | 0    | 0    | 0    | 0    | 0.50 | 0    | 0    | 0    | 0       | 0.50-1\nMOV -0x60(%RBP),%EDX                               | 1     | 0    | 0    | 0.50 | 0.50 | 0    | 0    | 0    | 0    | 0    | 0    | 2       | 0.50\nMOV -0x68(%RBP),%RCX                               | 1     | 0    | 0    | 0.50 | 0.50 | 0    | 0    | 0    | 0    | 0    | 0    | 2       | 0.50\nCMP $0x1,%EDX                                      | 1     | 0.25 | 0.25 | 0    | 0    | 0    | 0.25 | 0.25 | 0    | 0    | 0    | 1       | 0.25\nJE 2476f5 <PyUnicode_Format+0xe45>                 | 1     | 0.50 | 0    | 0    | 0    | 0    | 0    | 0.50 | 0    | 0    | 0    | 0       | 0.50-1\nCMP $0x2,%EDX                                      | 1     | 0.25 | 0.25 | 0    | 0    | 0    | 0.25 | 0.25 | 0    | 0    | 0    | 1       | 0.25\nJE 247d51 <PyUnicode_Format+0x14a1>                | 1     | 0.50 | 0    | 0    | 0    | 0    | 0    | 0.50 | 0    | 0    | 0    | 0       | 0.50-1\nMOVL $0x25,(%RCX,%RAX,4)                           | 1     | 0    | 0    | 0    | 0    | 0.50 | 0    | 0    | 0.50 | 0.50 | 0.50 | 2       | 0.50\nINC %RAX                                           | 1     | 0.25 | 0.25 | 0    | 0    | 0    | 0.25 | 0.25 | 0    | 0    | 0    | 1       | 0.25\nMOV %RAX,-0x50(%RBP)                               | 1     | 0    | 0    | 0    | 0    | 0.50 | 0    | 0    | 0.50 | 0.50 | 0.50 | 3       | 0.50\nJMP 246a9b <PyUnicode_Format+0x1eb>                | 1     | 0    | 0    | 0    | 0    | 0    | 0    | 1    | 0    | 0    | 0    | 0       | 1-2\nMOVZX 0x1(%RSI,%R8,1),%R15D                        | 1     | 0    | 0    | 0.50 | 0.50 | 0    | 0    | 0    | 0    | 0    | 0    | 1       | 0.50\nJMP 246b15 <PyUnicode_Format+0x265>                | 1     | 0    | 0    | 0    | 0    | 0    | 0    | 1    | 0    | 0    | 0    | 0       | 1-2\nMOV -0xd8(%RBP),%RDI                               | 1     | 0    | 0    | 0.50 | 0.50 | 0    | 0    | 0    | 0    | 0    | 0    | 2       | 0.50\nMOV $0x25,%EDX                                     | 1     | 0.25 | 0.25 | 0    | 0    | 0    | 0.25 | 0.25 | 0    | 0    | 0    | 1       | 0.25\nMOV $0x1,%ESI                                      | 1     | 0.25 | 0.25 | 0    | 0    | 0    | 0.25 | 0.25 | 0    | 0    | 0    | 1       | 0.25\nVZEROUPPER                                         | 4     | 0    | 0    | 0    | 0    | 0    | 0    | 0    | 0    | 0    | 0    | 0       | 1\nCALL 109410 <_PyUnicodeWriter_PrepareInternal@plt> | 2     | 0    | 0    | 0    | 0    | 0.50 | 0    | 1    | 0.50 | 0.50 | 0.50 | 0       | 2\nTEST %EAX,%EAX                                     | 1     | 0.25 | 0.25 | 0    | 0    | 0    | 0.25 | 0.25 | 0    | 0    | 0    | 1       | 0.25\nJS 246ff1 <PyUnicode_Format+0x741>                 | 1     | 0.50 | 0    | 0    | 0    | 0    | 0    | 0.50 | 0    | 0    | 0    | 0       | 0.50-1\nMOV -0x60(%RBP),%EDX                               | 1     | 0    | 0    | 0.50 | 0.50 | 0    | 0    | 0    | 0    | 0    | 0    | 2       | 0.50\nMOV -0x50(%RBP),%RAX                               | 1     | 0    | 0    | 0.50 | 0.50 | 0    | 0    | 0    | 0    | 0    | 0    | 2       | 0.50\nMOV -0x68(%RBP),%RCX                               | 1     | 0    | 0    | 0.50 | 0.50 | 0    | 0    | 0    | 0    | 0    | 0    | 2       | 0.50\nCMP $0x1,%EDX                                      | 1     | 0.25 | 0.25 | 0    | 0    | 0    | 0.25 | 0.25 | 0    | 0    | 0    | 1       | 0.25\nJNE 2474e4 <PyUnicode_Format+0xc34>                | 1     | 0.50 | 0    | 0    | 0    | 0    | 0    | 0.50 | 0    | 0    | 0    | 0       | 0.50-1\nMOVB $0x25,(%RCX,%RAX,1)                           | 1     | 0    | 0    | 0    | 0    | 0.50 | 0    | 0    | 0.50 | 0.50 | 0.50 | 2       | 0.50\nMOV -0x50(%RBP),%RAX                               | 1     | 0    | 0    | 0.50 | 0.50 | 0    | 0    | 0    | 0    | 0    | 0    | 2       | 0.50\nJMP 2474f4 <PyUnicode_Format+0xc44>                | 1     | 0    | 0    | 0    | 0    | 0    | 0    | 1    | 0    | 0    | 0    | 0       | 1-2\nMOV %RCX,-0x88(%RBP)                               | 1     | 0    | 0    | 0    | 0    | 0.50 | 0    | 0    | 0.50 | 0.50 | 0.50 | 3       | 0.50\nMOVZX 0x2(%RSI,%R10,1),%R15D                       | 1     | 0    | 0    | 0.50 | 0.50 | 0    | 0    | 0    | 0    | 0    | 0    | 1       | 0.50\nJMP 246b15 <PyUnicode_Format+0x265>                | 1     | 0    | 0    | 0    | 0    | 0    | 0    | 1    | 0    | 0    | 0    | 0       | 1-2\nMOV $0x25,%R9D                                     | 1     | 0.25 | 0.25 | 0    | 0    | 0    | 0.25 | 0.25 | 0    | 0    | 0    | 1       | 0.25\nMOV %R9W,(%RCX,%RAX,2)                             | 1     | 0    | 0    | 0    | 0    | 0.50 | 0    | 0    | 0.50 | 0.50 | 0.50 | 3       | 0.50\nJMP 2474f4 <PyUnicode_Format+0xc44>                | 1     | 0    | 0    | 0    | 0    | 0    | 0    | 1    | 0    | 0    | 0    | 0       | 1-2\n",
              },
            ],
          "header":
            [
            "Warnings:\nget_path_cqa_results:\n - Detected a function call instruction: ignoring called function instructions.\nRerun with --follow-calls=append to include them to analysis  or with --follow-calls=inline to simulate inlining.\n",
            "0% of peak computational performance is used (0.00 out of 64.00 FLOP per cycle (GFLOPS @ 1GHz))",
            ],
          "brief":
            [
            ],
          "gain":
            [
              {
                "workaround": " - Try another compiler or update/tune your current one:\n  * recompile with fassociative-math (included in Ofast or ffast-math) to extend loop vectorization to FP reductions.\n - Remove inter-iterations dependences from your loop and make it unit-stride:\n  * If your arrays have 2 or more dimensions, check whether elements are accessed contiguously and, otherwise, try to permute loops accordingly:\nC storage order is row-major: for(i) for(j) a[j][i] = b[j][i]; (slow, non stride 1) => for(i) for(j) a[i][j] = b[i][j]; (fast, stride 1)<<image_row_maj>>\n  * If your loop streams arrays of structures (AoS), try to use structures of arrays instead (SoA):\nfor(i) a[i].x = b[i].x; (slow, non stride 1) => for(i) a.x[i] = b.x[i]; (fast, stride 1)\n",
                "details": "Store and arithmetical SSE/AVX instructions are used in scalar version (process only one data element in vector registers).\nSince your execution units are vector units, only a vectorized loop can use their full power.\n",
                "title": "Vectorization",
                "txt": "Your loop is probably not vectorized.\nOnly 9% of vector register length is used (average across all SSE/AVX instructions).\nBy vectorizing your loop, you can lower the cost of an iteration from 24.00 to 2.33 cycles (10.31x speedup).",
              },
              {
                "title": "Execution units bottlenecks",
                "txt": "Found no such bottlenecks but see expert reports for more complex bottlenecks.",
              },
            ],
          "potential":
            [
            ],
        },
      "paths":
        [
          {
            "hint":
              [
                {
                  "details": "Calling (and then returning from) a function prevents many compiler optimizations (like vectorization), breaks control flow (which reduces pipeline performance) and executes extra instructions to save/restore the registers used inside it, which is very expensive (dozens of cycles). Consider to inline small functions.\n - _PyUnicodeWriter_PrepareInternal@plt: 1 occurrences\n - _PyUnicodeWriter_WriteSubstring@plt: 1 occurrences\n",
                  "title": "CALL instructions",
                  "txt": "Detected function call instructions.\n",
                },
                {
                  "details": "These instructions generate more than one micro-operation and only one of them can be decoded during a cycle and the extra micro-operations increase pressure on execution units.\n - VZEROUPPER: 2 occurrences\n",
                  "title": "Complex instructions",
                  "txt": "Detected COMPLEX INSTRUCTIONS.\n",
                },
                {
                  "title": "Type of elements and instruction set",
                  "txt": "No instructions are processing arithmetic or math operations on FP elements. This loop is probably writing/copying data or processing integer elements.",
                },
                {
                  "title": "Matching between your loop (in the source code) and the binary loop",
                  "txt": "The binary loop does not contain any FP arithmetical operations.\nThe binary loop is loading 150 bytes.\nThe binary loop is storing 152 bytes.",
                },
              ],
            "expert":
              [
                {
                  "title": "General properties",
                  "txt": "nb instructions    : 112\nnb uops            : 120\nloop length        : 540\nused x86 registers : 12\nused mmx registers : 0\nused xmm registers : 0\nused ymm registers : 0\nused zmm registers : 0\nnb stack references: 14\n",
                },
                {
                  "title": "Front-end",
                  "txt": "MACRO FUSION NOT POSSIBLE\nFIT IN UOP CACHE\nmicro-operation queue: 24.00 cycles\nfront end            : 24.00 cycles\n",
                },
                {
                  "title": "Back-end",
                  "txt": "       | P0    | P1    | P2    | P3    | P4    | P5    | P6    | P7    | P8    | P9\n--------------------------------------------------------------------------------------\nuops   | 15.75 | 15.75 | 12.50 | 12.50 | 12.00 | 15.75 | 15.75 | 12.00 | 12.00 | 12.00\ncycles | 15.75 | 15.75 | 12.50 | 12.50 | 12.00 | 15.75 | 15.75 | 12.00 | 12.00 | 12.00\n\nExecution ports to units layout:\n - P0 (256 bits): VPU, ALU, DIV/SQRT\n - P1 (256 bits): ALU, VPU\n - P2 (512 bits): load\n - P3 (512 bits): load\n - P4 (256 bits): store data\n - P5 (512 bits): ALU, VPU\n - P6: ALU\n - P7: store address\n - P8: store address\n - P9 (256 bits): store data\n\nCycles executing div or sqrt instructions: NA\n",
                },
                {
                  "title": "Cycles summary",
                  "txt": "Front-end : 24.00\nDispatch  : 15.75\nOverall L1: 24.00\n",
                },
                {
                  "title": "Vectorization ratios",
                  "txt": "all     : 4%\nload    : 0%\nstore   : 0%\nmul     : NA (no mul vectorizable/vectorized instructions)\nadd-sub : NA (no add-sub vectorizable/vectorized instructions)\nfma     : NA (no fma vectorizable/vectorized instructions)\ndiv/sqrt: NA (no div/sqrt vectorizable/vectorized instructions)\nother   : 11%\n",
                },
                {
                  "title": "Vector efficiency ratios",
                  "txt": "all     : 9%\nload    : 6%\nstore   : 10%\nmul     : NA (no mul vectorizable/vectorized instructions)\nadd-sub : NA (no add-sub vectorizable/vectorized instructions)\nfma     : NA (no fma vectorizable/vectorized instructions)\ndiv/sqrt: NA (no div/sqrt vectorizable/vectorized instructions)\nother   : 8%\n",
                },
                {
                  "title": "Cycles and memory resources usage",
                  "txt": "Assuming all data fit into the L1 cache, each iteration of the binary loop takes 24.00 cycles. At this rate:\n - 4% of peak load performance is reached (6.25 out of 128.00 bytes loaded per cycle (GB/s @ 1GHz))\n - 9% of peak store performance is reached (6.33 out of 64.00 bytes stored per cycle (GB/s @ 1GHz))\n",
                },
                {
                  "title": "Front-end bottlenecks",
                  "txt": "Performance is limited by instruction throughput (loading/decoding program instructions to execution core) (front-end is a bottleneck).\n\nBy removing all these bottlenecks, you can lower the cost of an iteration from 24.00 to 15.75 cycles (1.52x speedup).\n",
                },
                {
                  "title": "ASM code",
                  "txt": "In the binary file, the address of the loop is: 246a9b\n\nInstruction                                        | Nb FU | P0   | P1   | P2   | P3   | P4   | P5   | P6   | P7   | P8   | P9   | Latency | Recip. throughput\n--------------------------------------------------------------------------------------------------------------------------------------------------------------\nMOV -0x88(%RBP),%R8                                | 1     | 0    | 0    | 0.50 | 0.50 | 0    | 0    | 0    | 0    | 0    | 0    | 2       | 0.50\nMOV -0x98(%RBP),%EDX                               | 1     | 0    | 0    | 0.50 | 0.50 | 0    | 0    | 0    | 0    | 0    | 0    | 2       | 0.50\nMOV -0x80(%RBP),%RSI                               | 1     | 0    | 0    | 0.50 | 0.50 | 0    | 0    | 0    | 0    | 0    | 0    | 2       | 0.50\nMOV %EDX,%R9D                                      | 1     | 0.25 | 0.25 | 0    | 0    | 0    | 0.25 | 0.25 | 0    | 0    | 0    | 1       | 0.25\nLEA 0x1(%R8),%RCX                                  | 1     | 0.25 | 0.25 | 0    | 0    | 0    | 0.25 | 0.25 | 0    | 0    | 0    | 1       | 0.25\nCMP $0x1,%EDX                                      | 1     | 0.25 | 0.25 | 0    | 0    | 0    | 0.25 | 0.25 | 0    | 0    | 0    | 1       | 0.25\nJE 2473a0 <PyUnicode_Format+0xaf0>                 | 1     | 0.50 | 0    | 0    | 0    | 0    | 0    | 0.50 | 0    | 0    | 0    | 0       | 0.50-1\nCMP $0x2,%EDX                                      | 1     | 0.25 | 0.25 | 0    | 0    | 0    | 0.25 | 0.25 | 0    | 0    | 0    | 1       | 0.25\nJE 2473e8 <PyUnicode_Format+0xb38>                 | 1     | 0.50 | 0    | 0    | 0    | 0    | 0    | 0.50 | 0    | 0    | 0    | 0       | 0.50-1\nCMPL $0x25,(%RSI,%R8,4)                            | 1     | 0.25 | 0.25 | 0.50 | 0.50 | 0    | 0.25 | 0.25 | 0    | 0    | 0    | 1       | 0.50\nLEA (,%R8,4),%R10                                  | 1     | 0.25 | 0.25 | 0    | 0    | 0    | 0.25 | 0.25 | 0    | 0    | 0    | 1       | 0.25\nMOV %RCX,-0x88(%RBP)                               | 1     | 0    | 0    | 0    | 0    | 0.50 | 0    | 0    | 0.50 | 0.50 | 0.50 | 3       | 0.50\nJE 246b10 <PyUnicode_Format+0x260>                 | 1     | 0.50 | 0    | 0    | 0    | 0    | 0    | 0.50 | 0    | 0    | 0    | 0       | 0.50-1\nXOR %EDI,%EDI                                      | 1     | 0    | 0    | 0    | 0    | 0    | 0    | 0    | 0    | 0    | 0    | 0       | 0.25\nXOR %EDX,%EDX                                      | 1     | 0    | 0    | 0    | 0    | 0    | 0    | 0    | 0    | 0    | 0    | 0       | 0.25\nJMP 246a60 <PyUnicode_Format+0x1b0>                | 1     | 0    | 0    | 0    | 0    | 0    | 0    | 1    | 0    | 0    | 0    | 0       | 1-2\nTEST %DIL,%DIL                                     | 1     | 0.25 | 0.25 | 0    | 0    | 0    | 0.25 | 0.25 | 0    | 0    | 0    | 1       | 0.25\nJE 246a72 <PyUnicode_Format+0x1c2>                 | 1     | 0.50 | 0    | 0    | 0    | 0    | 0    | 0.50 | 0    | 0    | 0    | 0       | 0.50-1\nMOV %R13,-0x90(%RBP)                               | 1     | 0    | 0    | 0    | 0    | 0.50 | 0    | 0    | 0.50 | 0.50 | 0.50 | 3       | 0.50\nTEST %DL,%DL                                       | 1     | 0.25 | 0.25 | 0    | 0    | 0    | 0.25 | 0.25 | 0    | 0    | 0    | 1       | 0.25\nJE 246a7d <PyUnicode_Format+0x1cd>                 | 1     | 0.50 | 0    | 0    | 0    | 0    | 0    | 0.50 | 0    | 0    | 0    | 0       | 0.50-1\nMOV %R14,-0x88(%RBP)                               | 1     | 0    | 0    | 0    | 0    | 0.50 | 0    | 0    | 0.50 | 0.50 | 0.50 | 3       | 0.50\nMOV -0x78(%RBP),%RSI                               | 1     | 0    | 0    | 0.50 | 0.50 | 0    | 0    | 0    | 0    | 0    | 0    | 2       | 0.50\nMOV -0xd8(%RBP),%RDI                               | 1     | 0    | 0    | 0.50 | 0.50 | 0    | 0    | 0    | 0    | 0    | 0    | 2       | 0.50\nMOV %R8,%RDX                                       | 1     | 0.25 | 0.25 | 0    | 0    | 0    | 0.25 | 0.25 | 0    | 0    | 0    | 1       | 0.25\nVZEROUPPER                                         | 4     | 0    | 0    | 0    | 0    | 0    | 0    | 0    | 0    | 0    | 0    | 0       | 1\nCALL 1074f0 <_PyUnicodeWriter_WriteSubstring@plt>  | 2     | 0    | 0    | 0    | 0    | 0.50 | 0    | 1    | 0.50 | 0.50 | 0.50 | 0       | 2\nTEST %EAX,%EAX                                     | 1     | 0.25 | 0.25 | 0    | 0    | 0    | 0.25 | 0.25 | 0    | 0    | 0    | 1       | 0.25\nJS 246ff1 <PyUnicode_Format+0x741>                 | 1     | 0.50 | 0    | 0    | 0    | 0    | 0    | 0.50 | 0    | 0    | 0    | 0       | 0.50-1\nMOV -0x90(%RBP),%RDI                               | 1     | 0    | 0    | 0.50 | 0.50 | 0    | 0    | 0    | 0    | 0    | 0    | 2       | 0.50\nLEA -0x1(%RDI),%RAX                                | 1     | 0.25 | 0.25 | 0    | 0    | 0    | 0.25 | 0.25 | 0    | 0    | 0    | 1       | 0.25\nMOV %RAX,-0x90(%RBP)                               | 1     | 0    | 0    | 0    | 0    | 0.50 | 0    | 0    | 0.50 | 0.50 | 0.50 | 3       | 0.50\nTEST %RAX,%RAX                                     | 1     | 0.25 | 0.25 | 0    | 0    | 0    | 0.25 | 0.25 | 0    | 0    | 0    | 1       | 0.25\nJNS 2469e8 <PyUnicode_Format+0x138>                | 1     | 0.50 | 0    | 0    | 0    | 0    | 0    | 0.50 | 0    | 0    | 0    | 0       | 0.50-1\nMOV 0x4(%RSI,%R10,1),%R15D                         | 1     | 0    | 0    | 0.50 | 0.50 | 0    | 0    | 0    | 0    | 0    | 0    | 2       | 0.50\nCMP $0x25,%R15D                                    | 1     | 0.25 | 0.25 | 0    | 0    | 0    | 0.25 | 0.25 | 0    | 0    | 0    | 1       | 0.25\nJE 2474a0 <PyUnicode_Format+0xbf0>                 | 1     | 0.50 | 0    | 0    | 0    | 0    | 0    | 0.50 | 0    | 0    | 0    | 0       | 0.50-1\nMOV %R9,-0x108(%RBP)                               | 1     | 0    | 0    | 0    | 0    | 0.50 | 0    | 0    | 0.50 | 0.50 | 0.50 | 3       | 0.50\nMOV %R10,-0x100(%RBP)                              | 1     | 0    | 0    | 0    | 0    | 0.50 | 0    | 0    | 0.50 | 0.50 | 0.50 | 3       | 0.50\nMOVQ $-0x1,-0x90(%RBP)                             | 1     | 0    | 0    | 0    | 0    | 0.50 | 0    | 0    | 0.50 | 0.50 | 0.50 | 2       | 0.50\nDEC %RCX                                           | 1     | 0.25 | 0.25 | 0    | 0    | 0    | 0.25 | 0.25 | 0    | 0    | 0    | 1       | 0.25\nMOVB $0,-0x3c(%RBP)                                | 1     | 0    | 0    | 0    | 0    | 0.50 | 0    | 0    | 0.50 | 0.50 | 0.50 | 2       | 0.50\nMOV %RCX,-0x88(%RBP)                               | 1     | 0    | 0    | 0    | 0    | 0.50 | 0    | 0    | 0.50 | 0.50 | 0.50 | 3       | 0.50\nJMP 246a7d <PyUnicode_Format+0x1cd>                | 1     | 0    | 0    | 0    | 0    | 0    | 0    | 1    | 0    | 0    | 0    | 0       | 1-2\nCMPB $0x25,(%RSI,%R8,1)                            | 1     | 0.25 | 0.25 | 0.50 | 0.50 | 0    | 0.25 | 0.25 | 0    | 0    | 0    | 1       | 0.50\nMOV %RCX,-0x88(%RBP)                               | 1     | 0    | 0    | 0    | 0    | 0.50 | 0    | 0    | 0.50 | 0.50 | 0.50 | 3       | 0.50\nJNE 2473da <PyUnicode_Format+0xb2a>                | 1     | 0.50 | 0    | 0    | 0    | 0    | 0    | 0.50 | 0    | 0    | 0    | 0       | 0.50-1\nJMP 2476b0 <PyUnicode_Format+0xe00>                | 1     | 0    | 0    | 0    | 0    | 0    | 0    | 1    | 0    | 0    | 0    | 0       | 1-2\nJMP 246a7d <PyUnicode_Format+0x1cd>                | 1     | 0    | 0    | 0    | 0    | 0    | 0    | 1    | 0    | 0    | 0    | 0       | 1-2\nCMPW $0x25,(%RSI,%R8,2)                            | 1     | 0.25 | 0.25 | 0.50 | 0.50 | 0    | 0.25 | 0.25 | 0    | 0    | 0    | 1       | 0.50\nLEA (%R8,%R8,1),%R10                               | 1     | 0.25 | 0.25 | 0    | 0    | 0    | 0.25 | 0.25 | 0    | 0    | 0    | 1       | 0.25\nJE 247718 <PyUnicode_Format+0xe68>                 | 1     | 0.50 | 0    | 0    | 0    | 0    | 0    | 0.50 | 0    | 0    | 0    | 0       | 0.50-1\nMOV %RCX,-0x88(%RBP)                               | 1     | 0    | 0    | 0    | 0    | 0.50 | 0    | 0    | 0.50 | 0.50 | 0.50 | 3       | 0.50\nMOV -0x108(%RBP),%R9                               | 1     | 0    | 0    | 0.50 | 0.50 | 0    | 0    | 0    | 0    | 0    | 0    | 2       | 0.50\nXOR %EDI,%EDI                                      | 1     | 0    | 0    | 0    | 0    | 0    | 0    | 0    | 0    | 0    | 0    | 0       | 0.25\nXOR %EDX,%EDX                                      | 1     | 0    | 0    | 0    | 0    | 0    | 0    | 0    | 0    | 0    | 0    | 0       | 0.25\nMOV -0x100(%RBP),%R10                              | 1     | 0    | 0    | 0.50 | 0.50 | 0    | 0    | 0    | 0    | 0    | 0    | 2       | 0.50\nJMP 247460 <PyUnicode_Format+0xbb0>                | 1     | 0    | 0    | 0    | 0    | 0    | 0    | 1    | 0    | 0    | 0    | 0       | 1-2\nMOV %R9,-0x108(%RBP)                               | 1     | 0    | 0    | 0    | 0    | 0.50 | 0    | 0    | 0.50 | 0.50 | 0.50 | 3       | 0.50\nMOV %R10,-0x100(%RBP)                              | 1     | 0    | 0    | 0    | 0    | 0.50 | 0    | 0    | 0.50 | 0.50 | 0.50 | 3       | 0.50\nTEST %DIL,%DIL                                     | 1     | 0.25 | 0.25 | 0    | 0    | 0    | 0.25 | 0.25 | 0    | 0    | 0    | 1       | 0.25\nJE 247481 <PyUnicode_Format+0xbd1>                 | 1     | 0.50 | 0    | 0    | 0    | 0    | 0    | 0.50 | 0    | 0    | 0    | 0       | 0.50-1\nMOV %R9,-0x90(%RBP)                                | 1     | 0    | 0    | 0    | 0    | 0.50 | 0    | 0    | 0.50 | 0.50 | 0.50 | 3       | 0.50\nTEST %DL,%DL                                       | 1     | 0.25 | 0.25 | 0    | 0    | 0    | 0.25 | 0.25 | 0    | 0    | 0    | 1       | 0.25\nJE 246a7d <PyUnicode_Format+0x1cd>                 | 1     | 0.50 | 0    | 0    | 0    | 0    | 0    | 0.50 | 0    | 0    | 0    | 0       | 0.50-1\nMOV -0x100(%RBP),%RAX                              | 1     | 0    | 0    | 0.50 | 0.50 | 0    | 0    | 0    | 0    | 0    | 0    | 2       | 0.50\nMOV %RAX,-0x88(%RBP)                               | 1     | 0    | 0    | 0    | 0    | 0.50 | 0    | 0    | 0.50 | 0.50 | 0.50 | 3       | 0.50\nJMP 246a7d <PyUnicode_Format+0x1cd>                | 1     | 0    | 0    | 0    | 0    | 0    | 0    | 1    | 0    | 0    | 0    | 0       | 1-2\nADD $0x2,%R8                                       | 1     | 0.25 | 0.25 | 0    | 0    | 0    | 0.25 | 0.25 | 0    | 0    | 0    | 1       | 0.25\nSUB $0x2,%RDI                                      | 1     | 0.25 | 0.25 | 0    | 0    | 0    | 0.25 | 0.25 | 0    | 0    | 0    | 1       | 0.25\nCMPL $0x24,-0x5c(%RBP)                             | 1     | 0.25 | 0.25 | 0.50 | 0.50 | 0    | 0.25 | 0.25 | 0    | 0    | 0    | 1       | 0.50\nMOV %R8,-0x88(%RBP)                                | 1     | 0    | 0    | 0    | 0    | 0.50 | 0    | 0    | 0.50 | 0.50 | 0.50 | 3       | 0.50\nMOV %RDI,-0x90(%RBP)                               | 1     | 0    | 0    | 0    | 0    | 0.50 | 0    | 0    | 0.50 | 0.50 | 0.50 | 3       | 0.50\nJBE 2476c0 <PyUnicode_Format+0xe10>                | 1     | 0.50 | 0    | 0    | 0    | 0    | 0    | 0.50 | 0    | 0    | 0    | 0       | 0.50-1\nMOV -0x50(%RBP),%RAX                               | 1     | 0    | 0    | 0.50 | 0.50 | 0    | 0    | 0    | 0    | 0    | 0    | 2       | 0.50\nMOV -0x58(%RBP),%RDX                               | 1     | 0    | 0    | 0.50 | 0.50 | 0    | 0    | 0    | 0    | 0    | 0    | 2       | 0.50\nSUB %RAX,%RDX                                      | 1     | 0.25 | 0.25 | 0    | 0    | 0    | 0.25 | 0.25 | 0    | 0    | 0    | 1       | 0.25\nTEST %RDX,%RDX                                     | 1     | 0.25 | 0.25 | 0    | 0    | 0    | 0.25 | 0.25 | 0    | 0    | 0    | 1       | 0.25\nJLE 2476c0 <PyUnicode_Format+0xe10>                | 1     | 0.50 | 0    | 0    | 0    | 0    | 0    | 0.50 | 0    | 0    | 0    | 0       | 0.50-1\nMOV -0x60(%RBP),%EDX                               | 1     | 0    | 0    | 0.50 | 0.50 | 0    | 0    | 0    | 0    | 0    | 0    | 2       | 0.50\nMOV -0x68(%RBP),%RCX                               | 1     | 0    | 0    | 0.50 | 0.50 | 0    | 0    | 0    | 0    | 0    | 0    | 2       | 0.50\nCMP $0x1,%EDX                                      | 1     | 0.25 | 0.25 | 0    | 0    | 0    | 0.25 | 0.25 | 0    | 0    | 0    | 1       | 0.25\nJE 2476f5 <PyUnicode_Format+0xe45>                 | 1     | 0.50 | 0    | 0    | 0    | 0    | 0    | 0.50 | 0    | 0    | 0    | 0       | 0.50-1\nCMP $0x2,%EDX                                      | 1     | 0.25 | 0.25 | 0    | 0    | 0    | 0.25 | 0.25 | 0    | 0    | 0    | 1       | 0.25\nJE 247d51 <PyUnicode_Format+0x14a1>                | 1     | 0.50 | 0    | 0    | 0    | 0    | 0    | 0.50 | 0    | 0    | 0    | 0       | 0.50-1\nMOVL $0x25,(%RCX,%RAX,4)                           | 1     | 0    | 0    | 0    | 0    | 0.50 | 0    | 0    | 0.50 | 0.50 | 0.50 | 2       | 0.50\nINC %RAX                                           | 1     | 0.25 | 0.25 | 0    | 0    | 0    | 0.25 | 0.25 | 0    | 0    | 0    | 1       | 0.25\nMOV %RAX,-0x50(%RBP)                               | 1     | 0    | 0    | 0    | 0    | 0.50 | 0    | 0    | 0.50 | 0.50 | 0.50 | 3       | 0.50\nJMP 246a9b <PyUnicode_Format+0x1eb>                | 1     | 0    | 0    | 0    | 0    | 0    | 0    | 1    | 0    | 0    | 0    | 0       | 1-2\nMOVZX 0x1(%RSI,%R8,1),%R15D                        | 1     | 0    | 0    | 0.50 | 0.50 | 0    | 0    | 0    | 0    | 0    | 0    | 1       | 0.50\nJMP 246b15 <PyUnicode_Format+0x265>                | 1     | 0    | 0    | 0    | 0    | 0    | 0    | 1    | 0    | 0    | 0    | 0       | 1-2\nMOV -0xd8(%RBP),%RDI                               | 1     | 0    | 0    | 0.50 | 0.50 | 0    | 0    | 0    | 0    | 0    | 0    | 2       | 0.50\nMOV $0x25,%EDX                                     | 1     | 0.25 | 0.25 | 0    | 0    | 0    | 0.25 | 0.25 | 0    | 0    | 0    | 1       | 0.25\nMOV $0x1,%ESI                                      | 1     | 0.25 | 0.25 | 0    | 0    | 0    | 0.25 | 0.25 | 0    | 0    | 0    | 1       | 0.25\nVZEROUPPER                                         | 4     | 0    | 0    | 0    | 0    | 0    | 0    | 0    | 0    | 0    | 0    | 0       | 1\nCALL 109410 <_PyUnicodeWriter_PrepareInternal@plt> | 2     | 0    | 0    | 0    | 0    | 0.50 | 0    | 1    | 0.50 | 0.50 | 0.50 | 0       | 2\nTEST %EAX,%EAX                                     | 1     | 0.25 | 0.25 | 0    | 0    | 0    | 0.25 | 0.25 | 0    | 0    | 0    | 1       | 0.25\nJS 246ff1 <PyUnicode_Format+0x741>                 | 1     | 0.50 | 0    | 0    | 0    | 0    | 0    | 0.50 | 0    | 0    | 0    | 0       | 0.50-1\nMOV -0x60(%RBP),%EDX                               | 1     | 0    | 0    | 0.50 | 0.50 | 0    | 0    | 0    | 0    | 0    | 0    | 2       | 0.50\nMOV -0x50(%RBP),%RAX                               | 1     | 0    | 0    | 0.50 | 0.50 | 0    | 0    | 0    | 0    | 0    | 0    | 2       | 0.50\nMOV -0x68(%RBP),%RCX                               | 1     | 0    | 0    | 0.50 | 0.50 | 0    | 0    | 0    | 0    | 0    | 0    | 2       | 0.50\nCMP $0x1,%EDX                                      | 1     | 0.25 | 0.25 | 0    | 0    | 0    | 0.25 | 0.25 | 0    | 0    | 0    | 1       | 0.25\nJNE 2474e4 <PyUnicode_Format+0xc34>                | 1     | 0.50 | 0    | 0    | 0    | 0    | 0    | 0.50 | 0    | 0    | 0    | 0       | 0.50-1\nMOVB $0x25,(%RCX,%RAX,1)                           | 1     | 0    | 0    | 0    | 0    | 0.50 | 0    | 0    | 0.50 | 0.50 | 0.50 | 2       | 0.50\nMOV -0x50(%RBP),%RAX                               | 1     | 0    | 0    | 0.50 | 0.50 | 0    | 0    | 0    | 0    | 0    | 0    | 2       | 0.50\nJMP 2474f4 <PyUnicode_Format+0xc44>                | 1     | 0    | 0    | 0    | 0    | 0    | 0    | 1    | 0    | 0    | 0    | 0       | 1-2\nMOV %RCX,-0x88(%RBP)                               | 1     | 0    | 0    | 0    | 0    | 0.50 | 0    | 0    | 0.50 | 0.50 | 0.50 | 3       | 0.50\nMOVZX 0x2(%RSI,%R10,1),%R15D                       | 1     | 0    | 0    | 0.50 | 0.50 | 0    | 0    | 0    | 0    | 0    | 0    | 1       | 0.50\nJMP 246b15 <PyUnicode_Format+0x265>                | 1     | 0    | 0    | 0    | 0    | 0    | 0    | 1    | 0    | 0    | 0    | 0       | 1-2\nMOV $0x25,%R9D                                     | 1     | 0.25 | 0.25 | 0    | 0    | 0    | 0.25 | 0.25 | 0    | 0    | 0    | 1       | 0.25\nMOV %R9W,(%RCX,%RAX,2)                             | 1     | 0    | 0    | 0    | 0    | 0.50 | 0    | 0    | 0.50 | 0.50 | 0.50 | 3       | 0.50\nJMP 2474f4 <PyUnicode_Format+0xc44>                | 1     | 0    | 0    | 0    | 0    | 0    | 0    | 1    | 0    | 0    | 0    | 0       | 1-2\n",
                },
              ],
            "header":
              [
              "Warnings:\nget_path_cqa_results:\n - Detected a function call instruction: ignoring called function instructions.\nRerun with --follow-calls=append to include them to analysis  or with --follow-calls=inline to simulate inlining.\n",
              "0% of peak computational performance is used (0.00 out of 64.00 FLOP per cycle (GFLOPS @ 1GHz))",
              ],
            "brief":
              [
              ],
            "gain":
              [
                {
                  "workaround": " - Try another compiler or update/tune your current one:\n  * recompile with fassociative-math (included in Ofast or ffast-math) to extend loop vectorization to FP reductions.\n - Remove inter-iterations dependences from your loop and make it unit-stride:\n  * If your arrays have 2 or more dimensions, check whether elements are accessed contiguously and, otherwise, try to permute loops accordingly:\nC storage order is row-major: for(i) for(j) a[j][i] = b[j][i]; (slow, non stride 1) => for(i) for(j) a[i][j] = b[i][j]; (fast, stride 1)<<image_row_maj>>\n  * If your loop streams arrays of structures (AoS), try to use structures of arrays instead (SoA):\nfor(i) a[i].x = b[i].x; (slow, non stride 1) => for(i) a.x[i] = b.x[i]; (fast, stride 1)\n",
                  "details": "Store and arithmetical SSE/AVX instructions are used in scalar version (process only one data element in vector registers).\nSince your execution units are vector units, only a vectorized loop can use their full power.\n",
                  "title": "Vectorization",
                  "txt": "Your loop is probably not vectorized.\nOnly 9% of vector register length is used (average across all SSE/AVX instructions).\nBy vectorizing your loop, you can lower the cost of an iteration from 24.00 to 2.33 cycles (10.31x speedup).",
                },
                {
                  "title": "Execution units bottlenecks",
                  "txt": "Found no such bottlenecks but see expert reports for more complex bottlenecks.",
                },
              ],
            "potential":
              [
              ],
          },
        ],
      "common":
        {
          "header":
            [
            "The loop is defined in:\n - /tmp/python-build.20240827235536.29272/Python-3.12.0/./Include/cpython/unicodeobject.h:293-304,317-324\n - /tmp/python-build.20240827235536.29272/Python-3.12.0/Objects/unicodeobject.c:13075-13079,14272,14322-14324,14396-14416\n\n",
            "Warnings:\n - get_cqa_results:\n  * Non-innermost loop: analyzing only self part (ignoring child loops).\n  * Ignoring paths for analysis\n  * Failed to get the number of paths\n - metrics:\n  * RecMII not computed since number of paths is unknown or > max_paths\n  * Streams not analyzed since number of paths is unknown or > max_paths\n",
            ],
        },
    },
}
